cythonautoinstall/README.MD
cythonautoinstall/__init__.py
cythonautoinstall/requirements.txt
cythonautoinstall/thirdparty.json
cythonautoinstall-0.10.dist-info/LICENSE.rst
cythonautoinstall-0.10.dist-info/METADATA
cythonautoinstall-0.10.dist-info/WHEEL
cythonautoinstall-0.10.dist-info/top_level.txt
cythonautoinstall-0.10.dist-info/RECORD
