Metadata-Version: 2.1
Name: cythonautoinstall
Version: 0.10
Summary: Generates and installs simple Cython modules with specified settings. If you are overwhelmed by the compiler directives and the creation of the setup.py file, this is right for you.
Home-page: https://github.com/hansalemaos/cythonautoinstall
Author: Johannes Fischer
Author-email: aulasparticularesdealemaosp@gmail.com
License: MIT
Keywords: cython,compile,automatic
Classifier: Development Status :: 4 - Beta
Classifier: Programming Language :: Python :: 3 :: Only
Classifier: Programming Language :: Python :: 3.10
Classifier: Topic :: Software Development :: Libraries :: Python Modules
Classifier: Topic :: Utilities
License-File: LICENSE.rst
Requires-Dist: Cython
